{
    "game": {
        "id": "la",
        "name": "Links Reawakening",
        "width": 480,
        "height": 270,
        "fullscreen": false,
        "icon": "/img/icon/apple-icon.png",
        "version": 18
    },
    "hero": {
        "sprite": 1,
        "spawn": {
            "x": 768,
            "y": 736,
            "map": "/games/la/maps/mabe-village-west.json"
        }
    },
    "heroes": [
        {
            "id": "la",
            "name": "BK",
            "scale": 2,
            "width": 92,
            "height": 92,
            "image": "/games/la/assets/sprites/hero_la.png",
            "boxes": {
                "hit": {
                    "x": 28,
                    "y": 44,
                    "width": 36,
                    "height": 40
                }
            },
            "verbs": {
                "face": {
                    "dur": 240,
                    "down": {
                        "offsetX": 0,
                        "offsetY": 0,
                        "stepsX": 0
                    },
                    "up": {
                        "offsetX": -92,
                        "offsetY": 0,
                        "stepsX": 0
                    },
                    "left": {
                        "offsetX": -184,
                        "offsetY": 0,
                        "stepsX": 0
                    },
                    "right": {
                        "offsetX": -276,
                        "offsetY": 0,
                        "stepsX": 0
                    }
                },
                "walk": {
                    "dur": 240,
                    "down": {
                        "offsetX": 0,
                        "offsetY": -92,
                        "stepsX": 2
                    },
                    "up": {
                        "offsetX": 0,
                        "offsetY": -184,
                        "stepsX": 2
                    },
                    "left": {
                        "offsetX": 0,
                        "offsetY": -276,
                        "stepsX": 2
                    },
                    "right": {
                        "offsetX": 0,
                        "offsetY": -368,
                        "stepsX": 2
                    }
                },
                "push": {
                    "dur": 240,
                    "down": {
                        "offsetX": -184,
                        "offsetY": -92,
                        "stepsX": 2
                    },
                    "up": {
                        "offsetX": -184,
                        "offsetY": -184,
                        "stepsX": 2
                    },
                    "left": {
                        "offsetX": -184,
                        "offsetY": -276,
                        "stepsX": 2
                    },
                    "right": {
                        "offsetX": -184,
                        "offsetY": -368,
                        "stepsX": 2
                    }
                },
                "pull": {
                    "dur": 240,
                    "down": {
                        "offsetX": -368,
                        "offsetY": -92,
                        "stepsX": 2
                    },
                    "up": {
                        "offsetX": -368,
                        "offsetY": -184,
                        "stepsX": 2
                    },
                    "left": {
                        "offsetX": -368,
                        "offsetY": -276,
                        "stepsX": 2
                    },
                    "right": {
                        "offsetX": -368,
                        "offsetY": -368,
                        "stepsX": 2
                    }
                }
            }
        },
        {
            "id": "alttp",
            "name": "BK",
            "scale": 2.1875,
            "width": 140,
            "height": 140,
            "image": "/games/la/assets/sprites/hero_alttp.png",
            "boxes": {
                "hit": {
                    "x": 38,
                    "y": 58,
                    "width": 64,
                    "height": 60
                }
            },
            "verbs": {
                "face": {
                    "dur": 320,
                    "down": {
                        "offsetX": 0,
                        "offsetY": 0,
                        "stepsX": 0
                    },
                    "up": {
                        "offsetX": -140,
                        "offsetY": 0,
                        "stepsX": 0
                    },
                    "left": {
                        "offsetX": -280,
                        "offsetY": 0,
                        "stepsX": 0
                    },
                    "right": {
                        "offsetX": -420,
                        "offsetY": 0,
                        "stepsX": 0
                    }
                },
                "walk": {
                    "dur": 320,
                    "down": {
                        "offsetX": 0,
                        "offsetY": -140,
                        "stepsX": 8
                    },
                    "up": {
                        "offsetX": 0,
                        "offsetY": -280,
                        "stepsX": 8
                    },
                    "left": {
                        "offsetX": 0,
                        "offsetY": -420,
                        "stepsX": 8
                    },
                    "right": {
                        "offsetX": 0,
                        "offsetY": -560,
                        "stepsX": 8
                    }
                },
                "push": {
                    "dur": 320,
                    "down": {
                        "offsetX": 0,
                        "offsetY": -140,
                        "stepsX": 8
                    },
                    "up": {
                        "offsetX": 0,
                        "offsetY": -280,
                        "stepsX": 8
                    },
                    "left": {
                        "offsetX": 0,
                        "offsetY": -420,
                        "stepsX": 8
                    },
                    "right": {
                        "offsetX": 0,
                        "offsetY": -560,
                        "stepsX": 8
                    }
                },
                "pull": {
                    "dur": 320,
                    "down": {
                        "offsetX": 0,
                        "offsetY": -140,
                        "stepsX": 8
                    },
                    "up": {
                        "offsetX": 0,
                        "offsetY": -280,
                        "stepsX": 8
                    },
                    "left": {
                        "offsetX": 0,
                        "offsetY": -420,
                        "stepsX": 8
                    },
                    "right": {
                        "offsetX": 0,
                        "offsetY": -560,
                        "stepsX": 8
                    }
                }
            }
        }
    ],
    "objects": [
        {
            "id": "chimney-smoke",
            "name": "Chimney Smoke",
            "width": 32,
            "height": 32,
            "image": "/games/la/assets/sprites/smoke.png",
            "layer": "fg",
            "scale": 1,
            "states": [
                {
                    "bgp": {
                        "x": 0,
                        "y": 0
                    },
                    "animated": 1,
                    "offsetX": 0,
                    "offsetY": 0,
                    "stepsX": 4,
                    "dur": 2000
                }
            ]
        },
        {
            "id": "bird-statue",
            "name": "Bird Statue",
            "width": 64,
            "height": 128,
            "image": "/games/la/assets/tiles/tiles.png",
            "layer": "fg",
            "scale": 2,
            "boxes": {
                "hit": {
                    "x": 0,
                    "y": 64,
                    "width": 64,
                    "height": 64
                }
            }
        },
        {
            "id": "chest",
            "name": "Chest",
            "width": 64,
            "height": 64,
            "image": "/games/la/assets/tiles/tiles.png",
            "layer": "bg",
            "scale": 2,
            "boxes": {
                "hit": {
                    "x": 0,
                    "y": 0,
                    "width": 64,
                    "height": 64
                }
            }
        }
    ],
    "bundle": [
        "/games/la/assets/tiles/tiles.png",
        "/games/la/assets/sprites/smoke.png",
        "/games/la/assets/sprites/hero_la.png",
        "/games/la/assets/sprites/hero_alttp.png",
        "/games/la/assets/sounds/46-tal-tal-mountain-range.mp3",
        "/games/la/assets/sounds/40-animal-village.mp3",
        "/games/la/assets/sounds/30-richard-s-villa.mp3",
        "/games/la/assets/sounds/16-mysterious-forest.mp3",
        "/games/la/assets/sounds/11-mabe-village.mp3",
        "/games/la/assets/sounds/10-overworld.mp3",
        "/games/la/assets/sounds/07-koholint-island.mp3",
        "/games/la/maps/ukuku-prairie-west.json",
        "/games/la/maps/toronbo-shores-west.json",
        "/games/la/maps/toronbo-shores-east.json",
        "/games/la/maps/mysterious-forest.json",
        "/games/la/maps/mabe-village-west.json"
    ]
}