{
    "id": "beneath-the-rooster",
    "name": "Beneath the Rooster",
    "type": "indoor",
    "tilesize": 64,
    "width": 1280,
    "height": 1024,
    "tilewidth": 20,
    "tileheight": 16,
    "collider": 16,
    "image": "assets/tiles/tiles.png",
    "snapshot": "assets/snapshots/beneath-the-rooster.png",
    "thumbnail": "assets/snapshots/beneath-the-rooster-thumb.png",
    "sound": "assets/sounds/bgm-cave.mp3",
    "spawn": [
        {
            "x": 593,
            "y": 519,
            "dropin": true
        }
    ],
    "items": [],
    "fx": [],
    "tiles": [
        {
            "group": "pots",
            "layer": "background",
            "offsetX": 640,
            "offsetY": 384,
            "actions": [
                {
                    "verb": "lift",
                    "stat": {
                        "key": "strength",
                        "value": 1,
                        "dialogue": {
                            "type": "text",
                            "text": [
                                "This is too heavy for you!"
                            ]
                        }
                    }
                },
                {
                    "verb": "attack",
                    "fx": "smoke",
                    "drops": [
                        {
                            "id": "heart",
                            "chance": 20
                        },
                        {
                            "id": "green-rupee",
                            "chance": 20
                        },
                        {
                            "id": "blue-rupee",
                            "chance": 10
                        }
                    ]
                }
            ]
        },
        {
            "group": "torches",
            "layer": "background",
            "offsetX": 448,
            "offsetY": 2304,
            "stepsX": 4,
            "dur": 2000
        },
        {
            "group": "stones",
            "layer": "background",
            "offsetX": 192,
            "offsetY": 640,
            "actions": [
                {
                    "verb": "lift",
                    "stat": {
                        "key": "strength",
                        "value": 1,
                        "dialogue": {
                            "type": "text",
                            "text": [
                                "This is too heavy for you!"
                            ]
                        }
                    }
                }
            ]
        }
    ],
    "events": [
        {
            "coords": [
                11,
                5
            ],
            "type": "door",
            "map": "maps/lost-corner-of-the-world.json",
            "spawn": 2
        }
    ],
    "npcs": [
        {
            "id": "chest",
            "spawn": {
                "x": 384,
                "y": 448
            },
            "payload": {
                "quest": [
                    {
                        "type": "setItem",
                        "id": "feather",
                        "dialogue": {
                            "type": "text",
                            "text": [
                                "You got the Feather!",
                                "Now you can jump over gaps in the ground!"
                            ]
                        }
                    }
                ]
            }
        },
        {
            "id": "moblin",
            "spawn": {
                "x": 733,
                "y": 468
            },
            "ai": "roam",
            "type": "enemy",
            "action": {
                "verb": "attack"
            }
        }
    ],
    "collision": [
        [
            48,
            44
        ],
        [
            48,
            43
        ],
        [
            48,
            42
        ],
        [
            48,
            41
        ],
        [
            48,
            40
        ],
        [
            49,
            40
        ],
        [
            50,
            40
        ],
        [
            51,
            40
        ],
        [
            52,
            40
        ],
        [
            52,
            39
        ],
        [
            52,
            38
        ],
        [
            52,
            37
        ],
        [
            52,
            36
        ],
        [
            53,
            36
        ],
        [
            54,
            36
        ],
        [
            55,
            36
        ],
        [
            56,
            36
        ],
        [
            56,
            35
        ],
        [
            56,
            34
        ],
        [
            56,
            33
        ],
        [
            56,
            32
        ],
        [
            56,
            31
        ],
        [
            56,
            30
        ],
        [
            56,
            29
        ],
        [
            56,
            28
        ],
        [
            56,
            27
        ],
        [
            55,
            27
        ],
        [
            54,
            27
        ],
        [
            53,
            27
        ],
        [
            52,
            27
        ],
        [
            52,
            26
        ],
        [
            52,
            25
        ],
        [
            52,
            24
        ],
        [
            52,
            23
        ],
        [
            51,
            23
        ],
        [
            50,
            23
        ],
        [
            49,
            23
        ],
        [
            48,
            23
        ],
        [
            48,
            22
        ],
        [
            48,
            21
        ],
        [
            48,
            20
        ],
        [
            48,
            19
        ],
        [
            47,
            19
        ],
        [
            46,
            19
        ],
        [
            45,
            19
        ],
        [
            44,
            19
        ],
        [
            43,
            19
        ],
        [
            42,
            19
        ],
        [
            41,
            19
        ],
        [
            40,
            19
        ],
        [
            39,
            19
        ],
        [
            38,
            19
        ],
        [
            37,
            19
        ],
        [
            36,
            19
        ],
        [
            35,
            19
        ],
        [
            34,
            19
        ],
        [
            33,
            19
        ],
        [
            32,
            19
        ],
        [
            31,
            19
        ],
        [
            31,
            20
        ],
        [
            31,
            21
        ],
        [
            31,
            22
        ],
        [
            31,
            23
        ],
        [
            30,
            23
        ],
        [
            29,
            23
        ],
        [
            28,
            23
        ],
        [
            27,
            23
        ],
        [
            27,
            24
        ],
        [
            27,
            25
        ],
        [
            27,
            26
        ],
        [
            27,
            27
        ],
        [
            26,
            27
        ],
        [
            25,
            27
        ],
        [
            24,
            27
        ],
        [
            23,
            27
        ],
        [
            23,
            28
        ],
        [
            23,
            29
        ],
        [
            23,
            30
        ],
        [
            23,
            31
        ],
        [
            23,
            32
        ],
        [
            23,
            33
        ],
        [
            23,
            34
        ],
        [
            23,
            35
        ],
        [
            23,
            36
        ],
        [
            24,
            36
        ],
        [
            25,
            36
        ],
        [
            26,
            36
        ],
        [
            27,
            36
        ],
        [
            27,
            37
        ],
        [
            27,
            38
        ],
        [
            27,
            39
        ],
        [
            27,
            40
        ],
        [
            28,
            40
        ],
        [
            29,
            40
        ],
        [
            30,
            40
        ],
        [
            31,
            40
        ],
        [
            31,
            41
        ],
        [
            31,
            42
        ],
        [
            31,
            43
        ],
        [
            31,
            44
        ],
        [
            32,
            44
        ],
        [
            33,
            44
        ],
        [
            34,
            44
        ],
        [
            35,
            44
        ],
        [
            36,
            44
        ],
        [
            37,
            44
        ],
        [
            38,
            44
        ],
        [
            39,
            44
        ],
        [
            40,
            44
        ],
        [
            41,
            44
        ],
        [
            42,
            44
        ],
        [
            43,
            44
        ],
        [
            44,
            44
        ],
        [
            45,
            44
        ],
        [
            46,
            44
        ],
        [
            47,
            44
        ]
    ],
    "textures": {
        "background": [
            [
                0,
                0,
                0,
                0,
                0,
                0,
                0,
                0,
                0,
                0,
                0,
                0,
                0,
                0,
                0,
                0,
                0,
                0,
                0,
                0
            ],
            [
                0,
                0,
                0,
                0,
                0,
                0,
                0,
                0,
                0,
                0,
                0,
                0,
                0,
                0,
                0,
                0,
                0,
                0,
                0,
                0
            ],
            [
                0,
                0,
                0,
                0,
                0,
                0,
                0,
                0,
                0,
                0,
                0,
                0,
                0,
                0,
                0,
                0,
                0,
                0,
                0,
                0
            ],
            [
                0,
                0,
                0,
                0,
                0,
                0,
                0,
                0,
                0,
                0,
                0,
                0,
                0,
                0,
                0,
                0,
                0,
                0,
                0,
                0
            ],
            [
                0,
                0,
                0,
                0,
                0,
                [
                    [
                        448,
                        896
                    ],
                    [
                        448,
                        2304
                    ]
                ],
                [
                    [
                        384,
                        448
                    ],
                    [
                        448,
                        896
                    ]
                ],
                [
                    [
                        384,
                        448
                    ],
                    [
                        576,
                        896
                    ]
                ],
                [
                    [
                        384,
                        448
                    ],
                    [
                        448,
                        960
                    ]
                ],
                [
                    [
                        384,
                        448
                    ],
                    [
                        448,
                        960
                    ]
                ],
                [
                    [
                        384,
                        448
                    ],
                    [
                        448,
                        960
                    ]
                ],
                [
                    [
                        384,
                        448
                    ],
                    [
                        448,
                        960
                    ]
                ],
                [
                    [
                        384,
                        448
                    ],
                    [
                        640,
                        896
                    ]
                ],
                [
                    [
                        384,
                        448
                    ],
                    [
                        448,
                        896
                    ]
                ],
                [
                    [
                        448,
                        896
                    ],
                    [
                        448,
                        2304
                    ]
                ],
                0,
                0,
                0,
                0,
                0
            ],
            [
                0,
                0,
                0,
                0,
                0,
                [
                    [
                        384,
                        448
                    ],
                    [
                        448,
                        896
                    ]
                ],
                [
                    [
                        384,
                        448
                    ],
                    [
                        576,
                        896
                    ]
                ],
                [
                    [
                        384,
                        448
                    ],
                    [
                        512,
                        960
                    ]
                ],
                [
                    [
                        192,
                        384
                    ],
                    [
                        640,
                        384
                    ]
                ],
                [
                    [
                        192,
                        384
                    ]
                ],
                [
                    [
                        192,
                        384
                    ]
                ],
                [
                    [
                        192,
                        384
                    ],
                    [
                        256,
                        704
                    ]
                ],
                [
                    [
                        384,
                        448
                    ],
                    [
                        384,
                        960
                    ]
                ],
                [
                    [
                        384,
                        448
                    ],
                    [
                        640,
                        896
                    ]
                ],
                [
                    [
                        384,
                        448
                    ],
                    [
                        448,
                        896
                    ]
                ],
                0,
                0,
                0,
                0,
                0
            ],
            [
                0,
                0,
                0,
                0,
                0,
                [
                    [
                        384,
                        448
                    ],
                    [
                        576,
                        896
                    ]
                ],
                [
                    [
                        384,
                        448
                    ],
                    [
                        512,
                        960
                    ]
                ],
                [
                    [
                        192,
                        384
                    ],
                    [
                        640,
                        384
                    ]
                ],
                [
                    [
                        192,
                        384
                    ]
                ],
                [
                    [
                        192,
                        384
                    ]
                ],
                [
                    [
                        192,
                        384
                    ]
                ],
                [
                    [
                        192,
                        384
                    ]
                ],
                [
                    [
                        192,
                        384
                    ]
                ],
                [
                    [
                        384,
                        448
                    ],
                    [
                        384,
                        960
                    ]
                ],
                [
                    [
                        384,
                        448
                    ],
                    [
                        640,
                        896
                    ]
                ],
                0,
                0,
                0,
                0,
                0
            ],
            [
                0,
                0,
                0,
                0,
                0,
                [
                    [
                        384,
                        448
                    ],
                    [
                        512,
                        896
                    ]
                ],
                [
                    [
                        192,
                        384
                    ]
                ],
                [
                    [
                        192,
                        384
                    ]
                ],
                [
                    [
                        256,
                        2112
                    ]
                ],
                [
                    [
                        256,
                        2112
                    ]
                ],
                [
                    [
                        256,
                        2112
                    ]
                ],
                [
                    [
                        256,
                        2112
                    ]
                ],
                [
                    [
                        192,
                        384
                    ]
                ],
                [
                    [
                        192,
                        384
                    ],
                    [
                        640,
                        384
                    ]
                ],
                [
                    [
                        384,
                        448
                    ],
                    [
                        384,
                        896
                    ]
                ],
                0,
                0,
                0,
                0,
                0
            ],
            [
                0,
                0,
                0,
                0,
                0,
                [
                    [
                        384,
                        448
                    ],
                    [
                        512,
                        896
                    ]
                ],
                [
                    [
                        192,
                        384
                    ]
                ],
                [
                    [
                        192,
                        384
                    ]
                ],
                [
                    [
                        256,
                        2112
                    ]
                ],
                [
                    [
                        256,
                        2112
                    ]
                ],
                [
                    [
                        256,
                        2112
                    ]
                ],
                [
                    [
                        256,
                        2112
                    ]
                ],
                [
                    [
                        192,
                        384
                    ]
                ],
                [
                    [
                        192,
                        384
                    ],
                    [
                        640,
                        384
                    ]
                ],
                [
                    [
                        384,
                        448
                    ],
                    [
                        384,
                        896
                    ]
                ],
                0,
                0,
                0,
                0,
                0
            ],
            [
                0,
                0,
                0,
                0,
                0,
                [
                    [
                        384,
                        448
                    ],
                    [
                        576,
                        960
                    ]
                ],
                [
                    [
                        384,
                        448
                    ],
                    [
                        512,
                        832
                    ]
                ],
                [
                    [
                        192,
                        384
                    ]
                ],
                [
                    [
                        192,
                        384
                    ]
                ],
                [
                    [
                        256,
                        2112
                    ]
                ],
                [
                    [
                        256,
                        2112
                    ]
                ],
                [
                    [
                        192,
                        384
                    ]
                ],
                [
                    [
                        192,
                        384
                    ]
                ],
                [
                    [
                        384,
                        448
                    ],
                    [
                        384,
                        832
                    ]
                ],
                [
                    [
                        384,
                        448
                    ],
                    [
                        640,
                        960
                    ]
                ],
                0,
                0,
                0,
                0,
                0
            ],
            [
                0,
                0,
                0,
                0,
                0,
                [
                    [
                        448,
                        896
                    ]
                ],
                [
                    [
                        384,
                        448
                    ],
                    [
                        576,
                        960
                    ]
                ],
                [
                    [
                        384,
                        448
                    ],
                    [
                        512,
                        832
                    ]
                ],
                [
                    [
                        192,
                        384
                    ],
                    [
                        640,
                        384
                    ]
                ],
                [
                    [
                        192,
                        384
                    ],
                    [
                        640,
                        384
                    ]
                ],
                [
                    [
                        192,
                        384
                    ]
                ],
                [
                    [
                        192,
                        384
                    ],
                    [
                        640,
                        384
                    ]
                ],
                [
                    [
                        384,
                        448
                    ],
                    [
                        384,
                        832
                    ]
                ],
                [
                    [
                        384,
                        448
                    ],
                    [
                        640,
                        960
                    ]
                ],
                [
                    [
                        448,
                        896
                    ]
                ],
                0,
                0,
                0,
                0,
                0
            ],
            [
                0,
                0,
                0,
                0,
                0,
                [
                    [
                        448,
                        896
                    ],
                    [
                        448,
                        2304
                    ]
                ],
                [
                    [
                        384,
                        448
                    ],
                    [
                        448,
                        896
                    ]
                ],
                [
                    [
                        384,
                        448
                    ],
                    [
                        576,
                        960
                    ]
                ],
                [
                    [
                        384,
                        448
                    ],
                    [
                        448,
                        832
                    ]
                ],
                [
                    [
                        384,
                        448
                    ],
                    [
                        448,
                        832
                    ]
                ],
                [
                    [
                        384,
                        448
                    ],
                    [
                        448,
                        832
                    ]
                ],
                [
                    [
                        384,
                        448
                    ],
                    [
                        448,
                        832
                    ]
                ],
                [
                    [
                        384,
                        448
                    ],
                    [
                        640,
                        960
                    ]
                ],
                [
                    [
                        384,
                        448
                    ],
                    [
                        448,
                        896
                    ]
                ],
                [
                    [
                        448,
                        896
                    ],
                    [
                        448,
                        2304
                    ]
                ],
                0,
                0,
                0,
                0,
                0
            ],
            [
                0,
                0,
                0,
                0,
                0,
                0,
                0,
                0,
                0,
                0,
                0,
                0,
                0,
                0,
                0,
                0,
                0,
                0,
                0,
                0
            ],
            [
                0,
                0,
                0,
                0,
                0,
                0,
                0,
                0,
                0,
                0,
                0,
                0,
                0,
                0,
                0,
                0,
                0,
                0,
                0,
                0
            ],
            [
                0,
                0,
                0,
                0,
                0,
                0,
                0,
                0,
                0,
                0,
                0,
                0,
                0,
                0,
                0,
                0,
                0,
                0,
                0,
                0
            ],
            [
                0,
                0,
                0,
                0,
                0,
                0,
                0,
                0,
                0,
                0,
                0,
                0,
                0,
                0,
                0,
                0,
                0,
                0,
                0,
                0
            ]
        ],
        "foreground": [
            [
                0,
                0,
                0,
                0,
                0,
                0,
                0,
                0,
                0,
                0,
                0,
                0,
                0,
                0,
                0,
                0,
                0,
                0,
                0,
                0
            ],
            [
                0,
                0,
                0,
                0,
                0,
                0,
                0,
                0,
                0,
                0,
                0,
                0,
                0,
                0,
                0,
                0,
                0,
                0,
                0,
                0
            ],
            [
                0,
                0,
                0,
                0,
                0,
                0,
                0,
                0,
                0,
                0,
                0,
                0,
                0,
                0,
                0,
                0,
                0,
                0,
                0,
                0
            ],
            [
                0,
                0,
                0,
                0,
                0,
                0,
                0,
                0,
                0,
                0,
                0,
                0,
                0,
                0,
                0,
                0,
                0,
                0,
                0,
                0
            ],
            [
                0,
                0,
                0,
                0,
                0,
                0,
                0,
                0,
                0,
                0,
                0,
                0,
                0,
                0,
                0,
                0,
                0,
                0,
                0,
                0
            ],
            [
                0,
                0,
                0,
                0,
                0,
                0,
                0,
                0,
                0,
                0,
                0,
                0,
                0,
                0,
                0,
                0,
                0,
                0,
                0,
                0
            ],
            [
                0,
                0,
                0,
                0,
                0,
                0,
                0,
                0,
                0,
                0,
                0,
                0,
                0,
                0,
                0,
                0,
                0,
                0,
                0,
                0
            ],
            [
                0,
                0,
                0,
                0,
                0,
                0,
                0,
                0,
                0,
                0,
                0,
                0,
                0,
                0,
                0,
                0,
                0,
                0,
                0,
                0
            ],
            [
                0,
                0,
                0,
                0,
                0,
                0,
                0,
                0,
                0,
                0,
                0,
                0,
                0,
                0,
                0,
                0,
                0,
                0,
                0,
                0
            ],
            [
                0,
                0,
                0,
                0,
                0,
                0,
                0,
                0,
                0,
                0,
                0,
                0,
                0,
                0,
                0,
                0,
                0,
                0,
                0,
                0
            ],
            [
                0,
                0,
                0,
                0,
                0,
                0,
                0,
                0,
                0,
                0,
                0,
                0,
                0,
                0,
                0,
                0,
                0,
                0,
                0,
                0
            ],
            [
                0,
                0,
                0,
                0,
                0,
                0,
                0,
                0,
                0,
                0,
                0,
                0,
                0,
                0,
                0,
                0,
                0,
                0,
                0,
                0
            ],
            [
                0,
                0,
                0,
                0,
                0,
                0,
                0,
                0,
                0,
                0,
                0,
                0,
                0,
                0,
                0,
                0,
                0,
                0,
                0,
                0
            ],
            [
                0,
                0,
                0,
                0,
                0,
                0,
                0,
                0,
                0,
                0,
                0,
                0,
                0,
                0,
                0,
                0,
                0,
                0,
                0,
                0
            ],
            [
                0,
                0,
                0,
                0,
                0,
                0,
                0,
                0,
                0,
                0,
                0,
                0,
                0,
                0,
                0,
                0,
                0,
                0,
                0,
                0
            ],
            [
                0,
                0,
                0,
                0,
                0,
                0,
                0,
                0,
                0,
                0,
                0,
                0,
                0,
                0,
                0,
                0,
                0,
                0,
                0,
                0
            ]
        ]
    }
}